MANIFEST.in
README.md
setup.cfg
setup.py
docassemble/__init__.py
docassemble.gbls.egg-info/PKG-INFO
docassemble.gbls.egg-info/SOURCES.txt
docassemble.gbls.egg-info/dependency_links.txt
docassemble.gbls.egg-info/namespace_packages.txt
docassemble.gbls.egg-info/not-zip-safe
docassemble.gbls.egg-info/requires.txt
docassemble.gbls.egg-info/top_level.txt
docassemble/gbls/__init__.py
docassemble/gbls/household.py
docassemble/gbls/legal_server.py
docassemble/gbls/data/questions/basic-questions-gbls.yml
docassemble/gbls/data/questions/load_secret.yml
docassemble/gbls/data/questions/save_secret.yml
docassemble/gbls/data/sources/README.md
docassemble/gbls/data/static/README.md
docassemble/gbls/data/static/docassemble-ls.js
docassemble/gbls/data/templates/README.md