Metadata-Version: 2.1
Name: docassemble.gbls
Version: 0.0.55
Summary: Contains Legal Server integration, basic skeleton for interviews used at Greater Boston Legal Services
Home-page: https://docassemble.org
Author: Quinten Steenhuis
Author-email: admin@admin.com
License: The MIT License (MIT)
Platform: UNKNOWN
